idgxavier/CompletionLib.py
idgxavier/DFInfoLib.py
idgxavier/__init__.py
idgxavier/_version.py
idgxavier/utils.py
idgxavier/labextension/build_log.json
idgxavier/labextension/package.json
idgxavier/labextension/schemas/@xavier/idgxavier/completer.json
idgxavier/labextension/schemas/@xavier/idgxavier/package.json.orig
idgxavier/labextension/static/lib_index_js.7af5bdf42aad82443824.js
idgxavier/labextension/static/lib_index_js.7af5bdf42aad82443824.js.map
idgxavier/labextension/static/node_modules_nanoid_index_browser_js.18360d15bc081116b7e5.js
idgxavier/labextension/static/node_modules_nanoid_index_browser_js.18360d15bc081116b7e5.js.map
idgxavier/labextension/static/remoteEntry.1b089c076c626dd07905.js
idgxavier/labextension/static/remoteEntry.1b089c076c626dd07905.js.map
idgxavier/labextension/static/style.js
idgxavier/labextension/static/style_base_css.3b27ad6fb7e8bd2c597f.js
idgxavier/labextension/static/style_base_css.3b27ad6fb7e8bd2c597f.js.map
idgxavier/labextension/static/style_index_js.bd9def1fb78428f9959e.js
idgxavier/labextension/static/style_index_js.bd9def1fb78428f9959e.js.map
idgxavier/labextension/static/vendors-node_modules_lodash_lodash_js.cad6f638c12e4e75fa49.js
idgxavier/labextension/static/vendors-node_modules_lodash_lodash_js.cad6f638c12e4e75fa49.js.map
idgxavier/server/__init__.py
idgxavier/server/constant.py
idgxavier/server/datatypes.py
idgxavier/server/debugger.py
idgxavier/server/docCtrl.py
idgxavier/server/utils.py
idgxavier/server/lexAnalysis/analyzeConfig.py
idgxavier/server/lexAnalysis/fixJedi.py
idgxavier/server/lexAnalysis/pyParse.py
idgxavier/server/prompt/createPrompt.py
idgxavier/server/prompt/dataframeInfo.py
idgxavier/server/prompt/fmtCtrl.py
idgxavier/server/prompt/parseGPTOutput.py
idgxavier/server/prompt/share.py
idgxavier/server/server/apiFunc.py
idgxavier/server/server/myAIClient.py
idgxavier/server/trivial/specialCaseComplete.py
idgxavier/server/trivial/trivialComplete.py
idgxavier-0.0.1.dist-info/METADATA
idgxavier-0.0.1.dist-info/WHEEL
idgxavier-0.0.1.dist-info/RECORD
