Metadata-Version: 2.4
Name: idgxavier
Version: 0.0.1
Dynamic: Keywords
Summary: Minimal JupyterLab extension setting up the completion.
Project-URL: Homepage, https://github.com/CHI25-Xavier/Xavier
Project-URL: Bug Tracker, https://github.com/CHI25-Xavier/Xavier/issues
Project-URL: Repository, https://github.com/CHI25-Xavier/Xavier.git
Author: Project Jupyter Contributors
License: BSD-3-Clause License
Classifier: Framework :: Jupyter
Classifier: Framework :: Jupyter :: JupyterLab
Classifier: Framework :: Jupyter :: JupyterLab :: 4
Classifier: Framework :: Jupyter :: JupyterLab :: Extensions
Classifier: Framework :: Jupyter :: JupyterLab :: Extensions :: Prebuilt
Classifier: License :: OSI Approved :: BSD License
Classifier: Programming Language :: Python
Classifier: Programming Language :: Python :: 3
Classifier: Programming Language :: Python :: 3.8
Classifier: Programming Language :: Python :: 3.9
Classifier: Programming Language :: Python :: 3.10
Classifier: Programming Language :: Python :: 3.11
Classifier: Programming Language :: Python :: 3.12
Requires-Python: >=3.8
Requires-Dist: jupyterlab<5,>=4.0.0
Requires-Dist: openai
Requires-Dist: pandas>=2.2
Requires-Dist: typeguard<4
